CHANGES.txt
CONTRIBUTORS.txt
MANIFEST.in
README.rst
setup.py
./collective/__init__.py
./collective/recipe/__init__.py
./collective/recipe/pydevproject/__init__.py
./collective/recipe/pydevproject/tests/__init__.py
./collective/recipe/pydevproject/tests/test_docs.py
collective.recipe.pydevproject.egg-info/PKG-INFO
collective.recipe.pydevproject.egg-info/SOURCES.txt
collective.recipe.pydevproject.egg-info/dependency_links.txt
collective.recipe.pydevproject.egg-info/entry_points.txt
collective.recipe.pydevproject.egg-info/namespace_packages.txt
collective.recipe.pydevproject.egg-info/not-zip-safe
collective.recipe.pydevproject.egg-info/requires.txt
collective.recipe.pydevproject.egg-info/top_level.txt