Metadata-Version: 1.1
Name: collective.recipe.pydevproject
Version: 0.1
Summary: zc.buildout recipe that creates an Eclipse PyDev Project config with PYTHONPATH pointing to some eggs and their dependencies
Home-page: http://pypi.python.org/pypi/collective.recipe.pydevproject
Author: Marcio Mazza
Author-email: marciomazza@gmail.com
License: GPL
Keywords: buildout eggs eclipse pydev
Platform: UNKNOWN
Classifier: Framework :: Buildout
Classifier: Intended Audience :: Developers
Classifier: Topic :: Software Development :: Build Tools
Classifier: Topic :: Software Development :: Libraries :: Python Modules
Classifier: License :: OSI Approved :: GNU General Public License (GPL)
Classifier: Programming Language :: Python :: 2.4
Classifier: Programming Language :: Python :: 2.5
Classifier: Programming Language :: Python :: 2.6
Classifier: Programming Language :: Python :: 2.7
